[
  {
    "buildingType": "Barracks",
    "strength": 150,
    "constructionCost": [
      {
        "resourceName": "wood",
        "amount": 10
      },
      {
        "resourceName": "stone",
        "amount": 10
      }
    ],
    "productOfBuilding": [
      "Archer",
      "Spearman",
      "HeavyWarrior"
    ]
  },
  {
    "buildingType": "House",
    "strength": 100,
    "constructionCost": [
      {
        "resourceName": "wood",
        "amount": 10
      }
    ],
    "productOfBuilding": [
      "Builder"
    ]
  },
  {
    "buildingType": "Workshop",
    "strength": 150,
    "constructionCost": [
      {
        "resourceName": "wood",
        "amount": 15
      },
      {
        "resourceName": "metal",
        "amount": 5
      }
    ],
    "productOfBuilding": [
      "Catapult",
      "SiegeTower"
    ]
  },
  {
    "buildingType": "Temple",
    "strength": 125,
    "constructionCost": [
      {
        "resourceName": "wood",
        "amount": 10
      },
      {
        "resourceName": "stone",
        "amount": 10
      }
    ],
    "productOfBuilding": [
      "Healer"
    ]
  },
  {
    "buildingType": "Fields",
    "strength": 100,
    "constructionCost": [
      {
        "resourceName": "wood",
        "amount": 5
      }
    ],
    "productOfBuilding": [
      "Grain"
    ]
  },
  {
    "buildingType": "Mill",
    "strength": 125,
    "constructionCost": [
      {
        "resourceName": "wood",
        "amount": 10
      }
    ],
    "productOfBuilding": [
      "Food"
    ]
  },
  {
    "buildingType": "Watchtower",
    "strength": 150,
    "constructionCost": [
      {
        "resourceName": "wood",
        "amount": 15
      },
      {
        "resourceName": "stone",
        "amount": 10
      }
    ],
    "detectionRadius": 10.0,
    "buildingZoneRadius": 15.0,
    "archerCapacity": 5,
    "attackRange": [
      0,
      8
    ],
    "attackDelay": 2.0,
    "damagePerArcher": 5
  },
  {
    "buildingType": "Warehouse",
    "strength": 125,
    "constructionCost": [
      {
        "resourceName": "wood",
        "amount": 10
      },
      {
        "resourceName": "stone",
        "amount": 10
      }
    ],
    "resourceCapacityIncrease": true
  },
  {
    "buildingType": "TownHall",
    "strength": 150,
    "constructionCost": [
      {
        "resourceName": "wood",
        "amount": 20
      },
      {
        "resourceName": "stone",
        "amount": 20
      }
    ],
    "buildingZoneRadius": 20.0
  },
  {
    "buildingType": "Smeltery",
    "strength": 125,
    "constructionCost": [
      {
        "resourceName": "wood",
        "amount": 10
      },
      {
        "resourceName": "stone",
        "amount": 10
      }
    ],
    "productOfBuilding": [
      "metal"
    ]
  }
]